tjson/__init__.py
tjson/errors.py
tjson/py.typed
tjson/test_tjson.py
tjson/tjson.py
tj_json-1.0.2.dist-info/LICENSE
tj_json-1.0.2.dist-info/WHEEL
tj_json-1.0.2.dist-info/METADATA
tj_json-1.0.2.dist-info/RECORD
