Metadata-Version: 2.1
Name: tj-json
Version: 1.0.2
Summary: Accesss utility for JSON-shaped Python objects
Home-page: https://github.com/fsufitch/tjson
License: MIT
Author: Filip Sufitchi
Author-email: fsufitchi@gmail.com
Requires-Python: >=3.8,<4.0
Classifier: License :: OSI Approved :: MIT License
Classifier: Programming Language :: Python :: 3
Classifier: Programming Language :: Python :: 3.10
Classifier: Programming Language :: Python :: 3.8
Classifier: Programming Language :: Python :: 3.9
Project-URL: Repository, https://github.com/fsufitch/tjson
